boost_wrapper/__init__.py
boost_wrapper/logger.py
boost_wrapper/model_factory.py
boost_wrapper/param_utils.py
boost_wrapper/wrapper.py
boost_wrapper-0.1.0.dist-info/METADATA
boost_wrapper-0.1.0.dist-info/WHEEL
boost_wrapper-0.1.0.dist-info/top_level.txt
boost_wrapper-0.1.0.dist-info/RECORD
